async_eval/__init__.py
async_eval/async_eval.py
async_eval/asyncio_patch.py
async_eval/ext/__init__.py
async_eval/ext/pydevd/__init__.py
async_eval/ext/pydevd/code.py
async_eval/ext/pydevd/integration.py
async_eval-0.3.1.dist-info/LICENSE
async_eval-0.3.1.dist-info/METADATA
async_eval-0.3.1.dist-info/WHEEL
async_eval-0.3.1.dist-info/RECORD
