Metadata-Version: 2.1
Name: async-eval
Version: 0.3.1
Summary: eval async code from sync
Home-page: https://github.com/uriyyo/async-eval
License: MIT
Author: Yurii Karabas
Author-email: 1998uriyyo@gmail.com
Requires-Python: >=3.7,<4.0
Classifier: License :: OSI Approved :: MIT License
Classifier: Programming Language :: Python :: 3
Classifier: Programming Language :: Python :: 3.7
Classifier: Programming Language :: Python :: 3.8
Classifier: Programming Language :: Python :: 3.9
Classifier: Programming Language :: Python :: 3.10
Classifier: Programming Language :: Python :: 3.11
Provides-Extra: all
Provides-Extra: pydevd-pycharm
Provides-Extra: trio
Requires-Dist: pydevd-pycharm (>=232.8660.147) ; extra == "pydevd-pycharm" or extra == "all"
Requires-Dist: trio (>=0.21) ; extra == "trio" or extra == "all"
Project-URL: Repository, https://github.com/uriyyo/async-eval
